ChangeLog
MANIFEST.in
README.md
README.rst
example.json
example.py
example_multi.json
example_multi.py
jsonToCsv
setup.py
doc/index.html
doc/json_to_csv._private.html
doc/json_to_csv.help.html
doc/json_to_csv.html
jsonToCsv.egg-info/PKG-INFO
jsonToCsv.egg-info/SOURCES.txt
jsonToCsv.egg-info/dependency_links.txt
jsonToCsv.egg-info/top_level.txt
json_to_csv/__init__.py
json_to_csv/_private.py
json_to_csv/help.py