Metadata-Version: 1.1
Name: jsonToCsv
Version: 1.0.1
Summary: Extract data from json and convert to CSV
Home-page: https://github.com/kata198/jsonToCsv
Author: Tim Savannah
Author-email: kata198@gmail.com
License: LGPLv3
Keywords: json,to,csv,convert,extract,parse,rfc4180,text/csv,jsonToCsv
Platform: UNKNOWN
Classifier: Development Status :: 5 - Production/Stable
Classifier: Programming Language :: Python
Classifier: License :: OSI Approved :: GNU Lesser General Public License v3 (LGPLv3)
Classifier: Programming Language :: Python :: 2
Classifier: Programming Language :: Python :: 2
Classifier: Programming Language :: Python :: 2.7
Classifier: Programming Language :: Python :: 3
Classifier: Programming Language :: Python :: 3.4
Classifier: Programming Language :: Python :: 3.5
Classifier: Programming Language :: Python :: 3.6
Classifier: Topic :: Internet :: WWW/HTTP
Classifier: Topic :: Text Processing :: Markup :: HTML
Classifier: Topic :: Software Development :: Libraries :: Python Modules
